google_duylk/__init__.py
google_duylk/user_agents.txt.gz
google_duylk_monitaz-1.0.2.data/scripts/google
googlesearch/__init__.py
googlesearch/user_agents.txt.gz
google_duylk_monitaz-1.0.2.dist-info/METADATA
google_duylk_monitaz-1.0.2.dist-info/WHEEL
google_duylk_monitaz-1.0.2.dist-info/top_level.txt
google_duylk_monitaz-1.0.2.dist-info/RECORD
