Metadata-Version: 2.1
Name: google-duylk-monitaz
Version: 1.0.2
Summary: Python bindings to the Google search engine.
Home-page: https://techz.asia
Author: KhuongDuy
Author-email: leduyptit@gmail.com
License: UNKNOWN
Platform: UNKNOWN
Classifier: Development Status :: 5 - Production/Stable
Classifier: Intended Audience :: Developers
Classifier: License :: OSI Approved :: BSD License
Classifier: Environment :: Console
Classifier: Programming Language :: Python
Classifier: Topic :: Software Development :: Libraries :: Python Modules
Requires: beautifulsoup4
Provides: google_duylk
Requires-Dist: beautifulsoup4
